multivitamin/__init__.py
multivitamin/server.py
multivitamin/version.py
multivitamin/web_server.py
multivitamin/apis/__init__.py
multivitamin/apis/comm_api.py
multivitamin/apis/config.py
multivitamin/apis/http_api.py
multivitamin/apis/local_api.py
multivitamin/apis/s3_api.py
multivitamin/apis/sqs_api.py
multivitamin/applications/__init__.py
multivitamin/applications/utils.py
multivitamin/applications/images/__init__.py
multivitamin/applications/images/frame_drawer.py
multivitamin/applications/images/frame_extractor.py
multivitamin/applications/images/classifiers/__init__.py
multivitamin/applications/images/classifiers/caffe_classifier.py
multivitamin/applications/images/classifiers/pyt_classifier.py
multivitamin/applications/images/detectors/__init__.py
multivitamin/applications/images/detectors/ssd_detector.py
multivitamin/applications/images/detectors/tf_detector.py
multivitamin/applications/text/__init__.py
multivitamin/data/__init__.py
multivitamin/data/request.py
multivitamin/data/response/__init__.py
multivitamin/data/response/config.py
multivitamin/data/response/dtypes.py
multivitamin/data/response/io.py
multivitamin/data/response/response.py
multivitamin/data/response/schema.avsc
multivitamin/data/response/utils.py
multivitamin/media/__init__.py
multivitamin/media/file_retriever.py
multivitamin/media/http_fileobj.py
multivitamin/media/media_retriever.py
multivitamin/media/opencv_media_retriever.py
multivitamin/media/pims_media_retriever.py
multivitamin/module/__init__.py
multivitamin/module/codes.py
multivitamin/module/imagesmodule.py
multivitamin/module/module.py
multivitamin/module/propertiesmodule.py
multivitamin/module/utils.py
multivitamin/utils/GPUUtilities.py
multivitamin/utils/__init__.py
multivitamin/utils/work_handler.py
multivitamin-1.3.23.dist-info/LICENSE
multivitamin-1.3.23.dist-info/METADATA
multivitamin-1.3.23.dist-info/WHEEL
multivitamin-1.3.23.dist-info/top_level.txt
multivitamin-1.3.23.dist-info/RECORD
