Metadata-Version: 2.1
Name: multivitamin
Version: 1.3.23
Summary: Serving infrastructure for ML and CV models
Home-page: https://bitbucket.org/gumgum/multivitamin/
Author: GumGum ML
Author-email: UNKNOWN
License: UNKNOWN
Platform: UNKNOWN
Requires-Dist: gputil (==1.3.0)
Requires-Dist: colour (==0.1.5)
Requires-Dist: atomicwrites (==1.1.5)
Requires-Dist: attrs (==18.1.0)
Requires-Dist: avro-python3 (==1.8.2)
Requires-Dist: boto3
Requires-Dist: botocore (==1.12.86)
Requires-Dist: certifi
Requires-Dist: chardet (==3.0.4)
Requires-Dist: click (==6.7)
Requires-Dist: Cython (==0.28.3)
Requires-Dist: decorator (==4.3.0)
Requires-Dist: docopt (==0.6.2)
Requires-Dist: docutils (==0.14)
Requires-Dist: fastavro (==0.19.7)
Requires-Dist: Flask (==1.0.2)
Requires-Dist: flask-cors
Requires-Dist: glog (==0.3.1)
Requires-Dist: idna (==2.7)
Requires-Dist: itsdangerous (==0.24)
Requires-Dist: Jinja2 (==2.10)
Requires-Dist: jmespath (==0.9.3)
Requires-Dist: MarkupSafe (==1.0)
Requires-Dist: more-itertools (==4.2.0)
Requires-Dist: networkx (==2.1)
Requires-Dist: numpy (==1.14.5)
Requires-Dist: pandas (==0.23.1)
Requires-Dist: Pillow (==5.1.0)
Requires-Dist: pipreqs (==0.4.9)
Requires-Dist: pluggy (==0.6.0)
Requires-Dist: py (==1.5.3)
Requires-Dist: pytest (==3.6.2)
Requires-Dist: python-dateutil (>=2.7.5)
Requires-Dist: python-gflags (==3.1.2)
Requires-Dist: python-magic (==0.4.15)
Requires-Dist: pytz (==2018.4)
Requires-Dist: PyYAML (==3.13)
Requires-Dist: redis (==2.10.6)
Requires-Dist: requests (==2.19.1)
Requires-Dist: requests-testadapter (==0.3.0)
Requires-Dist: rq (==0.12.0)
Requires-Dist: s3transfer (==0.1.13)
Requires-Dist: scipy (==1.1.0)
Requires-Dist: six (==1.11.0)
Requires-Dist: tabulate (==0.8.2)
Requires-Dist: urllib3 (==1.23)
Requires-Dist: Werkzeug (==0.14.1)
Requires-Dist: yarg (==0.1.9)
Requires-Dist: matplotlib (==2.2.2)
Requires-Dist: confluent-kafka (==0.11.6)
Requires-Dist: zipfile2 (==0.0.12)
Requires-Dist: credstash (==1.15.0)
Requires-Dist: sphinx-nameko-theme
Requires-Dist: tqdm
Requires-Dist: dataclasses
Requires-Dist: typeguard
Requires-Dist: imohash
Requires-Dist: cupy-cuda80
Requires-Dist: pims
